tests/__init__.py
tests/eventkit/__init__.py
tests/eventkit/aggregate_test.py
tests/eventkit/combine_test.py
tests/eventkit/create_test.py
tests/eventkit/event_test.py
tests/eventkit/select_test.py
tests/eventkit/timing_test.py
tests/eventkit/transform_test.py
tests/nest_asyncio/__init__.py
tests/nest_asyncio/nest_test.py
ib_interface-0.0.3.dist-info/LICENSE
ib_interface-0.0.3.dist-info/METADATA
ib_interface-0.0.3.dist-info/WHEEL
ib_interface-0.0.3.dist-info/top_level.txt
ib_interface-0.0.3.dist-info/RECORD
