Metadata-Version: 2.1
Name: ib_interface
Version: 0.0.3
Summary: A Python Framework for Interactive Brokers TWS API
Home-page: https://github.com/jxtngx/ib-interface
Author: Justin Goheen
Author-email: 
License: Apache 2.0
Classifier: Topic :: Office/Business :: Financial :: Investment
Classifier: Operating System :: OS Independent
Classifier: Programming Language :: Python :: 3.11
License-File: LICENSE
Requires-Dist: numpy
Requires-Dist: pandas
Requires-Dist: matplotlib
Provides-Extra: dev
Requires-Dist: ruff ; extra == 'dev'
Requires-Dist: black ; extra == 'dev'
Requires-Dist: flake8 ; extra == 'dev'
Requires-Dist: pytest ; extra == 'dev'
Requires-Dist: pytest-asyncio ; extra == 'dev'
Requires-Dist: mypy ; extra == 'dev'
Requires-Dist: bandit ; extra == 'dev'
Requires-Dist: coverage ; extra == 'dev'
Requires-Dist: pre-commit ; extra == 'dev'
Requires-Dist: isort ; extra == 'dev'
Provides-Extra: dev-all
Requires-Dist: ib-interface[dev,docs] ; extra == 'dev-all'
Provides-Extra: docs
Requires-Dist: mkdocs-material ; extra == 'docs'
Requires-Dist: mkdocstrings[python] ; extra == 'docs'
Requires-Dist: mkdocs-glightbox ; extra == 'docs'
